AUTHORS
CHANGELOG
INSTALL
LICENSE
MANIFEST.in
README
setup.py
wardrobe/__init__.py
wardrobe/stackeddict.py
wardrobe/version.txt
wardrobe.egg-info/PKG-INFO
wardrobe.egg-info/SOURCES.txt
wardrobe.egg-info/dependency_links.txt
wardrobe.egg-info/not-zip-safe
wardrobe.egg-info/requires.txt
wardrobe.egg-info/top_level.txt