Metadata-Version: 1.0
Name: wardrobe
Version: 0.1
Summary: Stack-based datastructures: StackedDict.
Home-page: https://github.com/benoitbryon/wardrobe
Author: Benoit Bryon
Author-email: benoit@marmelune.net
License: BSD
Keywords: stack dict context
Platform: UNKNOWN
Classifier: Development Status :: 4 - Beta
Classifier: License :: OSI Approved :: BSD License
Classifier: Programming Language :: Python :: 2.7
